MANIFEST.in
README.md
requirements.txt
setup.cfg
setup.py
version.txt
agile_analytics/__init__.py
agile_analytics/analyzers.py
agile_analytics/fetchers.py
agile_analytics/models.py
agile_analytics/reporters.py
agile_analytics/version.py
agile_analytics/writers.py
agile_analytics.egg-info/PKG-INFO
agile_analytics.egg-info/SOURCES.txt
agile_analytics.egg-info/dependency_links.txt
agile_analytics.egg-info/requires.txt
agile_analytics.egg-info/top_level.txt
agile_analytics.egg-info/zip-safe