Metadata-Version: 1.1
Name: agile-analytics
Version: 0.15.1
Summary: Pulls data from agile systems and analyzes it.
Home-page: https://github.com/cmheisel/agile-analytics
Author: cmheisel
Author-email: chris@heisel.org
License: MIT License
Keywords: jira agile lean kanban metrics
Platform: UNKNOWN
Classifier: Development Status :: 3 - Alpha
Classifier: Intended Audience :: Information Technology
Classifier: Programming Language :: Python
Classifier: Programming Language :: Python :: 3
Classifier: Topic :: Software Development :: Libraries :: Python Modules
Classifier: Topic :: Utilities
Classifier: License :: OSI Approved :: MIT License
